vscoscrape/__init__.py
vscoscrape/constants.py
vscoscrape/vscoscrape.py
yjb_scraper-2.0.dist-info/LICENSE.txt
yjb_scraper-2.0.dist-info/METADATA
yjb_scraper-2.0.dist-info/WHEEL
yjb_scraper-2.0.dist-info/entry_points.txt
yjb_scraper-2.0.dist-info/top_level.txt
yjb_scraper-2.0.dist-info/RECORD
